{
 "slug": "sauna--kinosaki",
 "condition": {
  "slug": "sauna",
  "label": "サウナ"
 },
 "area": {
  "slug": "kinosaki",
  "label": "城崎",
  "officialName": "城崎温泉・豊岡・出石・神鍋"
 },
 "dataAsOf": "2026-07-16",
 "detection": {
  "type": "facility"
 },
 "stats": {
  "matchCount": 17,
  "matchRate": 18.9,
  "denominator": {
   "type": "listed_top",
   "value": 90,
   "label": "当サイト掲載施設(人気上位)数"
  },
  "minPrice": 3000,
  "medianPrice": 9900,
  "reviewAvgMean": 4.4,
  "pricedCount": 17
 },
 "hotels": [
  {
   "hotelNo": 19704,
   "name": "城崎温泉旅館　赤石屋",
   "kana": "きのさきおんせんりょかん　あかいしや",
   "minCharge": 13200,
   "reviewAverage": 4.79,
   "reviewCount": 60,
   "access": "ＪＲ城崎駅より徒歩5分／外湯「地蔵湯」の隣です。",
   "address1": "兵庫県",
   "address2": "豊岡市城崎町湯島786",
   "infoUrl": "https://hb.afl.rakuten.co.jp/hgc/1b181ff9.a7b47385.1b181ffa.294cb7e7/?pc=https%3A%2F%2Fimg.travel.rakuten.co.jp%2Fimage%2Ftr%2Fapi%2Fhs%2FdQ4dX%2F%3Ff_no%3D19704",
   "planUrl": "https://hb.afl.rakuten.co.jp/hgc/1b181ff9.a7b47385.1b181ffa.294cb7e7/?pc=https%3A%2F%2Fimg.travel.rakuten.co.jp%2Fimage%2Ftr%2Fapi%2Fhs%2FcHNRi%2F%3Ff_no%3D19704%26f_flg%3DPLAN",
   "reviewUrl": "https://hb.afl.rakuten.co.jp/hgc/1b181ff9.a7b47385.1b181ffa.294cb7e7/?pc=https%3A%2F%2Fimg.travel.rakuten.co.jp%2Fimage%2Ftr%2Fapi%2Fhs%2FRmfmX%2F%3Ff_hotel_no%3D19704",
   "thumbnail": "https://img.travel.rakuten.co.jp/HIMG/90/19704.jpg",
   "imageUrl": "https://img.travel.rakuten.co.jp/share/HOTEL/19704/19704.jpg",
   "special": "まちを愉しむ。ゆったりととのう。宿泊＆朝食の新スタイル旅館。"
  },
  {
   "hotelNo": 7597,
   "name": "城崎温泉　泉翠（せんすい）",
   "kana": "きのさきおんせん　せんすい",
   "minCharge": 13200,
   "reviewAverage": 4.74,
   "reviewCount": 758,
   "access": "ＪＲ西日本　山陰本線　城崎温泉駅下車徒歩８分。北近畿豊岡道（豊岡出石ICIC)より約20分",
   "address1": "兵庫県",
   "address2": "豊岡市城崎町湯島753",
   "infoUrl": "https://hb.afl.rakuten.co.jp/hgc/1b181ff9.a7b47385.1b181ffa.294cb7e7/?pc=https%3A%2F%2Fimg.travel.rakuten.co.jp%2Fimage%2Ftr%2Fapi%2Fhs%2FdQ4dX%2F%3Ff_no%3D7597",
   "planUrl": "https://hb.afl.rakuten.co.jp/hgc/1b181ff9.a7b47385.1b181ffa.294cb7e7/?pc=https%3A%2F%2Fimg.travel.rakuten.co.jp%2Fimage%2Ftr%2Fapi%2Fhs%2FcHNRi%2F%3Ff_no%3D7597%26f_flg%3DPLAN",
   "reviewUrl": "https://hb.afl.rakuten.co.jp/hgc/1b181ff9.a7b47385.1b181ffa.294cb7e7/?pc=https%3A%2F%2Fimg.travel.rakuten.co.jp%2Fimage%2Ftr%2Fapi%2Fhs%2FRmfmX%2F%3Ff_hotel_no%3D7597",
   "thumbnail": "https://img.travel.rakuten.co.jp/HIMG/90/7597.jpg",
   "imageUrl": "https://img.travel.rakuten.co.jp/share/HOTEL/7597/7597.jpg",
   "special": "温泉街中心に位置する大人限定の宿。サウナ付貸切風呂もオープン 館内の貸切風呂も無料で利用可"
  },
  {
   "hotelNo": 14007,
   "name": "城崎温泉　西村屋ホテル招月庭",
   "kana": "きのさきおんせん　にしむらやほてる　しょうげつてい",
   "minCharge": 35200,
   "reviewAverage": 4.74,
   "reviewCount": 1140,
   "access": "【電車】JR城崎温泉駅から旅館組合無料乗合バスで5～15分【車】北近畿豊岡自動車道・豊岡出石ICから約18分",
   "address1": "兵庫県",
   "address2": "豊岡市城崎町湯島1016-2",
   "infoUrl": "https://hb.afl.rakuten.co.jp/hgc/1b181ff9.a7b47385.1b181ffa.294cb7e7/?pc=https%3A%2F%2Fimg.travel.rakuten.co.jp%2Fimage%2Ftr%2Fapi%2Fhs%2FdQ4dX%2F%3Ff_no%3D14007",
   "planUrl": "https://hb.afl.rakuten.co.jp/hgc/1b181ff9.a7b47385.1b181ffa.294cb7e7/?pc=https%3A%2F%2Fimg.travel.rakuten.co.jp%2Fimage%2Ftr%2Fapi%2Fhs%2FcHNRi%2F%3Ff_no%3D14007%26f_flg%3DPLAN",
   "reviewUrl": "https://hb.afl.rakuten.co.jp/hgc/1b181ff9.a7b47385.1b181ffa.294cb7e7/?pc=https%3A%2F%2Fimg.travel.rakuten.co.jp%2Fimage%2Ftr%2Fapi%2Fhs%2FRmfmX%2F%3Ff_hotel_no%3D14007",
   "thumbnail": "https://img.travel.rakuten.co.jp/HIMG/90/14007.jpg",
   "imageUrl": "https://img.travel.rakuten.co.jp/share/HOTEL/14007/14007.jpg",
   "special": "かに・但馬牛など四季折々の味覚と充実したお風呂。五万坪の森林に囲まれ寛ぎのひとときを。無料駐車場有"
  },
  {
   "hotelNo": 176571,
   "name": "城崎温泉　きのさきの宿　緑風閣",
   "kana": "きのさきおんせん　きのさきのやど　りょくふうかく",
   "minCharge": 17000,
   "reviewAverage": 4.66,
   "reviewCount": 699,
   "access": "城崎温泉駅より徒歩にて約３分、専用駐車場は徒歩1分",
   "address1": "兵庫県",
   "address2": "豊岡市城崎町湯島174",
   "infoUrl": "https://hb.afl.rakuten.co.jp/hgc/1b181ff9.a7b47385.1b181ffa.294cb7e7/?pc=https%3A%2F%2Fimg.travel.rakuten.co.jp%2Fimage%2Ftr%2Fapi%2Fhs%2FdQ4dX%2F%3Ff_no%3D176571",
   "planUrl": "https://hb.afl.rakuten.co.jp/hgc/1b181ff9.a7b47385.1b181ffa.294cb7e7/?pc=https%3A%2F%2Fimg.travel.rakuten.co.jp%2Fimage%2Ftr%2Fapi%2Fhs%2FcHNRi%2F%3Ff_no%3D176571%26f_flg%3DPLAN",
   "reviewUrl": "https://hb.afl.rakuten.co.jp/hgc/1b181ff9.a7b47385.1b181ffa.294cb7e7/?pc=https%3A%2F%2Fimg.travel.rakuten.co.jp%2Fimage%2Ftr%2Fapi%2Fhs%2FRmfmX%2F%3Ff_hotel_no%3D176571",
   "thumbnail": "https://img.travel.rakuten.co.jp/HIMG/90/176571.jpg",
   "imageUrl": "https://img.travel.rakuten.co.jp/share/HOTEL/176571/176571.jpg",
   "special": "部屋食でゆっくり、サウナでととのう。家族旅行にも記念日にも選ばれる、城崎温泉駅徒歩3分の宿。"
  },
  {
   "hotelNo": 153168,
   "name": "竹野の海辺　湯やど　海の音〜うみのね〜",
   "kana": "たけののうみべ　ゆやど　うみのね〜うみのね〜",
   "minCharge": 27600,
   "reviewAverage": 4.61,
   "reviewCount": 322,
   "access": "ＪＲ　山陰本線　竹野駅よりお車にて約５分（送迎車あり）/城崎温泉駅よりお車にて約１５分/香住駅よりお車にて約３０分",
   "address1": "兵庫県",
   "address2": "豊岡市竹野町竹野3396-1",
   "infoUrl": "https://hb.afl.rakuten.co.jp/hgc/1b181ff9.a7b47385.1b181ffa.294cb7e7/?pc=https%3A%2F%2Fimg.travel.rakuten.co.jp%2Fimage%2Ftr%2Fapi%2Fhs%2FdQ4dX%2F%3Ff_no%3D153168",
   "planUrl": "https://hb.afl.rakuten.co.jp/hgc/1b181ff9.a7b47385.1b181ffa.294cb7e7/?pc=https%3A%2F%2Fimg.travel.rakuten.co.jp%2Fimage%2Ftr%2Fapi%2Fhs%2FcHNRi%2F%3Ff_no%3D153168%26f_flg%3DPLAN",
   "reviewUrl": "https://hb.afl.rakuten.co.jp/hgc/1b181ff9.a7b47385.1b181ffa.294cb7e7/?pc=https%3A%2F%2Fimg.travel.rakuten.co.jp%2Fimage%2Ftr%2Fapi%2Fhs%2FRmfmX%2F%3Ff_hotel_no%3D153168",
   "thumbnail": "https://img.travel.rakuten.co.jp/HIMG/90/153168.jpg",
   "imageUrl": "https://img.travel.rakuten.co.jp/share/HOTEL/153168/153168.jpg",
   "special": "城崎１５分全室オーシャンビュー♪美と健康の女子力ＵＰの宿★時を気にしない贅沢なひと時★カニ＆但馬牛"
  },
  {
   "hotelNo": 18412,
   "name": "城崎温泉　かがり火の宿　大西屋水翔苑",
   "kana": "きのさきおんせん　かがりびのやど　おおにしやすいしょうえん",
   "minCharge": 9230,
   "reviewAverage": 4.59,
   "reviewCount": 612,
   "access": "お車：北近畿豊岡自動車道(但馬空港IC最終)より25分、JR城崎温泉駅より組合無料バス（チェックインバス）で約5分",
   "address1": "兵庫県",
   "address2": "豊岡市城崎町桃島1256番地",
   "infoUrl": "https://hb.afl.rakuten.co.jp/hgc/1b181ff9.a7b47385.1b181ffa.294cb7e7/?pc=https%3A%2F%2Fimg.travel.rakuten.co.jp%2Fimage%2Ftr%2Fapi%2Fhs%2FdQ4dX%2F%3Ff_no%3D18412",
   "planUrl": "https://hb.afl.rakuten.co.jp/hgc/1b181ff9.a7b47385.1b181ffa.294cb7e7/?pc=https%3A%2F%2Fimg.travel.rakuten.co.jp%2Fimage%2Ftr%2Fapi%2Fhs%2FcHNRi%2F%3Ff_no%3D18412%26f_flg%3DPLAN",
   "reviewUrl": "https://hb.afl.rakuten.co.jp/hgc/1b181ff9.a7b47385.1b181ffa.294cb7e7/?pc=https%3A%2F%2Fimg.travel.rakuten.co.jp%2Fimage%2Ftr%2Fapi%2Fhs%2FRmfmX%2F%3Ff_hotel_no%3D18412",
   "thumbnail": "https://img.travel.rakuten.co.jp/HIMG/90/18412.jpg",
   "imageUrl": "https://img.travel.rakuten.co.jp/share/HOTEL/18412/18412.jpg",
   "special": "中庭にはかがり火の演出、廊下は畳敷き、ロビーで無料のコーヒー、サウナと水風呂あり。"
  },
  {
   "hotelNo": 145406,
   "name": "豊岡グリーンホテルモーリス",
   "kana": "とよおかぐりーんほてるもーりす",
   "minCharge": 5005,
   "reviewAverage": 4.53,
   "reviewCount": 2425,
   "access": "豊岡駅より徒歩にて約５分",
   "address1": "兵庫県",
   "address2": "豊岡市千代田町6-32",
   "infoUrl": "https://hb.afl.rakuten.co.jp/hgc/1b181ff9.a7b47385.1b181ffa.294cb7e7/?pc=https%3A%2F%2Fimg.travel.rakuten.co.jp%2Fimage%2Ftr%2Fapi%2Fhs%2FdQ4dX%2F%3Ff_no%3D145406",
   "planUrl": "https://hb.afl.rakuten.co.jp/hgc/1b181ff9.a7b47385.1b181ffa.294cb7e7/?pc=https%3A%2F%2Fimg.travel.rakuten.co.jp%2Fimage%2Ftr%2Fapi%2Fhs%2FcHNRi%2F%3Ff_no%3D145406%26f_flg%3DPLAN",
   "reviewUrl": "https://hb.afl.rakuten.co.jp/hgc/1b181ff9.a7b47385.1b181ffa.294cb7e7/?pc=https%3A%2F%2Fimg.travel.rakuten.co.jp%2Fimage%2Ftr%2Fapi%2Fhs%2FRmfmX%2F%3Ff_hotel_no%3D145406",
   "thumbnail": "https://img.travel.rakuten.co.jp/HIMG/90/145406.jpg",
   "imageUrl": "https://img.travel.rakuten.co.jp/share/HOTEL/145406/145406.jpg",
   "special": "JR豊岡駅まで徒歩5分。館内にレストラン・大浴場あります。予約受付は3か月前から受付開始。"
  },
  {
   "hotelNo": 5307,
   "name": "城崎温泉　川口屋城崎リバーサイドホテル",
   "kana": "きのさきおんせん　かわぐちや　きのさきりばーさいどほてる",
   "minCharge": 9900,
   "reviewAverage": 4.52,
   "reviewCount": 538,
   "access": "北近畿豊岡道　但馬空港Ｉ．Ｃより国道９号約２５分。",
   "address1": "兵庫県",
   "address2": "豊岡市城崎町湯島880-1",
   "infoUrl": "https://hb.afl.rakuten.co.jp/hgc/1b181ff9.a7b47385.1b181ffa.294cb7e7/?pc=https%3A%2F%2Fimg.travel.rakuten.co.jp%2Fimage%2Ftr%2Fapi%2Fhs%2FdQ4dX%2F%3Ff_no%3D5307",
   "planUrl": "https://hb.afl.rakuten.co.jp/hgc/1b181ff9.a7b47385.1b181ffa.294cb7e7/?pc=https%3A%2F%2Fimg.travel.rakuten.co.jp%2Fimage%2Ftr%2Fapi%2Fhs%2FcHNRi%2F%3Ff_no%3D5307%26f_flg%3DPLAN",
   "reviewUrl": "https://hb.afl.rakuten.co.jp/hgc/1b181ff9.a7b47385.1b181ffa.294cb7e7/?pc=https%3A%2F%2Fimg.travel.rakuten.co.jp%2Fimage%2Ftr%2Fapi%2Fhs%2FRmfmX%2F%3Ff_hotel_no%3D5307",
   "thumbnail": "https://img.travel.rakuten.co.jp/HIMG/90/5307.jpg",
   "imageUrl": "https://img.travel.rakuten.co.jp/share/HOTEL/5307/5307.jpg",
   "special": "展望貸切露天と美食が自慢。地蟹から但馬牛まで地元グルメ堪能♪客室・食事処など続々リニューアル中！"
  },
  {
   "hotelNo": 191796,
   "name": "ＨＯＳＴＥＬ　わらく",
   "kana": "ほすてる　わらく",
   "minCharge": 9900,
   "reviewAverage": 4.4,
   "reviewCount": 10,
   "access": "城崎温泉駅より徒歩約７分",
   "address1": "兵庫県",
   "address2": "豊岡市城崎町湯島831-3",
   "infoUrl": "https://hb.afl.rakuten.co.jp/hgc/1b181ff9.a7b47385.1b181ffa.294cb7e7/?pc=https%3A%2F%2Fimg.travel.rakuten.co.jp%2Fimage%2Ftr%2Fapi%2Fhs%2FdQ4dX%2F%3Ff_no%3D191796",
   "planUrl": "https://hb.afl.rakuten.co.jp/hgc/1b181ff9.a7b47385.1b181ffa.294cb7e7/?pc=https%3A%2F%2Fimg.travel.rakuten.co.jp%2Fimage%2Ftr%2Fapi%2Fhs%2FcHNRi%2F%3Ff_no%3D191796%26f_flg%3DPLAN",
   "reviewUrl": "https://hb.afl.rakuten.co.jp/hgc/1b181ff9.a7b47385.1b181ffa.294cb7e7/?pc=https%3A%2F%2Fimg.travel.rakuten.co.jp%2Fimage%2Ftr%2Fapi%2Fhs%2FRmfmX%2F%3Ff_hotel_no%3D191796",
   "thumbnail": "https://img.travel.rakuten.co.jp/HIMG/90/191796.jpg",
   "imageUrl": "https://img.travel.rakuten.co.jp/share/HOTEL/191796/191796.jpg",
   "special": "【城崎温泉＋αの集中ケアを】鍼灸サロンが営むスモールホテル◆バレルサウナ（屋外）併設"
  },
  {
   "hotelNo": 7020,
   "name": "日和山温泉　ホテル金波楼",
   "kana": "きんぱろう",
   "minCharge": 16600,
   "reviewAverage": 4.37,
   "reviewCount": 538,
   "access": "城崎マリンワールド隣接（ホテル宿泊者は入場半額券付）城崎温泉駅車約10分（送迎予約制）（城崎温泉街散策バス運行）",
   "address1": "兵庫県",
   "address2": "豊岡市瀬戸1090",
   "infoUrl": "https://hb.afl.rakuten.co.jp/hgc/1b181ff9.a7b47385.1b181ffa.294cb7e7/?pc=https%3A%2F%2Fimg.travel.rakuten.co.jp%2Fimage%2Ftr%2Fapi%2Fhs%2FdQ4dX%2F%3Ff_no%3D7020",
   "planUrl": "https://hb.afl.rakuten.co.jp/hgc/1b181ff9.a7b47385.1b181ffa.294cb7e7/?pc=https%3A%2F%2Fimg.travel.rakuten.co.jp%2Fimage%2Ftr%2Fapi%2Fhs%2FcHNRi%2F%3Ff_no%3D7020%26f_flg%3DPLAN",
   "reviewUrl": "https://hb.afl.rakuten.co.jp/hgc/1b181ff9.a7b47385.1b181ffa.294cb7e7/?pc=https%3A%2F%2Fimg.travel.rakuten.co.jp%2Fimage%2Ftr%2Fapi%2Fhs%2FRmfmX%2F%3Ff_hotel_no%3D7020",
   "thumbnail": "https://img.travel.rakuten.co.jp/HIMG/90/7020.jpg",
   "imageUrl": "https://img.travel.rakuten.co.jp/share/HOTEL/7020/7020.jpg",
   "special": "城崎マリンワールド徒歩１分！日本海の迫力ある大パノラマ絶景に露天風呂★城崎温泉車10分（送迎あり）"
  },
  {
   "hotelNo": 67969,
   "name": "城崎温泉　千年の湯古まん",
   "kana": "きのさきおんせん　せんねんのゆこまん",
   "minCharge": 9900,
   "reviewAverage": 4.36,
   "reviewCount": 264,
   "access": "JR山陰本線　城崎温泉駅から無料送迎バスにて５分",
   "address1": "兵庫県",
   "address2": "豊岡市城崎町湯島481",
   "infoUrl": "https://hb.afl.rakuten.co.jp/hgc/1b181ff9.a7b47385.1b181ffa.294cb7e7/?pc=https%3A%2F%2Fimg.travel.rakuten.co.jp%2Fimage%2Ftr%2Fapi%2Fhs%2FdQ4dX%2F%3Ff_no%3D67969",
   "planUrl": "https://hb.afl.rakuten.co.jp/hgc/1b181ff9.a7b47385.1b181ffa.294cb7e7/?pc=https%3A%2F%2Fimg.travel.rakuten.co.jp%2Fimage%2Ftr%2Fapi%2Fhs%2FcHNRi%2F%3Ff_no%3D67969%26f_flg%3DPLAN",
   "reviewUrl": "https://hb.afl.rakuten.co.jp/hgc/1b181ff9.a7b47385.1b181ffa.294cb7e7/?pc=https%3A%2F%2Fimg.travel.rakuten.co.jp%2Fimage%2Ftr%2Fapi%2Fhs%2FRmfmX%2F%3Ff_hotel_no%3D67969",
   "thumbnail": "https://img.travel.rakuten.co.jp/HIMG/90/67969.jpg",
   "imageUrl": "https://img.travel.rakuten.co.jp/share/HOTEL/67969/67969.jpg",
   "special": "城崎温泉開湯の宿。情緒深い町並みに映える純日本建築。「古木良木宿〜ふるきよきやど〜」"
  },
  {
   "hotelNo": 128351,
   "name": "ホテルシルク温泉やまびこ",
   "kana": "しるくおんせん　やまびこ",
   "minCharge": 7060,
   "reviewAverage": 4.33,
   "reviewCount": 406,
   "access": "☆1泊2食の方に限り福知山駅送迎OK♪13時福知山駅発　翌11時10分当館発要予約",
   "address1": "兵庫県",
   "address2": "豊岡市但東町正法寺165",
   "infoUrl": "https://hb.afl.rakuten.co.jp/hgc/1b181ff9.a7b47385.1b181ffa.294cb7e7/?pc=https%3A%2F%2Fimg.travel.rakuten.co.jp%2Fimage%2Ftr%2Fapi%2Fhs%2FdQ4dX%2F%3Ff_no%3D128351",
   "planUrl": "https://hb.afl.rakuten.co.jp/hgc/1b181ff9.a7b47385.1b181ffa.294cb7e7/?pc=https%3A%2F%2Fimg.travel.rakuten.co.jp%2Fimage%2Ftr%2Fapi%2Fhs%2FcHNRi%2F%3Ff_no%3D128351%26f_flg%3DPLAN",
   "reviewUrl": "https://hb.afl.rakuten.co.jp/hgc/1b181ff9.a7b47385.1b181ffa.294cb7e7/?pc=https%3A%2F%2Fimg.travel.rakuten.co.jp%2Fimage%2Ftr%2Fapi%2Fhs%2FRmfmX%2F%3Ff_hotel_no%3D128351",
   "thumbnail": "https://img.travel.rakuten.co.jp/HIMG/90/128351.jpg",
   "imageUrl": "https://img.travel.rakuten.co.jp/share/HOTEL/128351/128351.jpg",
   "special": "とろっと極上泉質美人の湯♪じゅわっとろける但馬牛石焼に朝食はあの但熊たまごのたまごかけごはんも♪"
  },
  {
   "hotelNo": 130498,
   "name": "大江戸温泉物語Ｐｒｅｍｉｕｍ　きのさき",
   "kana": "おおえどおんせんものがたりぷれみあむ　きのさき",
   "minCharge": 14800,
   "reviewAverage": 4.17,
   "reviewCount": 2487,
   "access": "城崎温泉駅⇒当館　旅館組合の送迎バス（詳しい出発時間は駅舎の係員にお尋ね下さい）",
   "address1": "兵庫県",
   "address2": "豊岡市城崎町桃島1232",
   "infoUrl": "https://hb.afl.rakuten.co.jp/hgc/1b181ff9.a7b47385.1b181ffa.294cb7e7/?pc=https%3A%2F%2Fimg.travel.rakuten.co.jp%2Fimage%2Ftr%2Fapi%2Fhs%2FdQ4dX%2F%3Ff_no%3D130498",
   "planUrl": "https://hb.afl.rakuten.co.jp/hgc/1b181ff9.a7b47385.1b181ffa.294cb7e7/?pc=https%3A%2F%2Fimg.travel.rakuten.co.jp%2Fimage%2Ftr%2Fapi%2Fhs%2FcHNRi%2F%3Ff_no%3D130498%26f_flg%3DPLAN",
   "reviewUrl": "https://hb.afl.rakuten.co.jp/hgc/1b181ff9.a7b47385.1b181ffa.294cb7e7/?pc=https%3A%2F%2Fimg.travel.rakuten.co.jp%2Fimage%2Ftr%2Fapi%2Fhs%2FRmfmX%2F%3Ff_hotel_no%3D130498",
   "thumbnail": "https://img.travel.rakuten.co.jp/HIMG/90/130498.jpg",
   "imageUrl": "https://img.travel.rakuten.co.jp/share/HOTEL/130498/130498.jpg",
   "special": "プレミアムラウンジで贅沢な時間を満喫。くつろぎの和モダン温泉宿"
  },
  {
   "hotelNo": 8778,
   "name": "神鍋温泉　自然に癒される高原ホテル　ブルーリッジホテル",
   "kana": "かんなべおんせん　しぜんにいやされるこうげんほてる　ぶるーりっじほてる",
   "minCharge": 14000,
   "reviewAverage": 4.07,
   "reviewCount": 703,
   "access": "播但連絡道路・北近畿豊岡自動車道　日高神鍋高原ＩＣより　１５分",
   "address1": "兵庫県",
   "address2": "豊岡市日高町栗栖野55",
   "infoUrl": "https://hb.afl.rakuten.co.jp/hgc/1b181ff9.a7b47385.1b181ffa.294cb7e7/?pc=https%3A%2F%2Fimg.travel.rakuten.co.jp%2Fimage%2Ftr%2Fapi%2Fhs%2FdQ4dX%2F%3Ff_no%3D8778",
   "planUrl": "https://hb.afl.rakuten.co.jp/hgc/1b181ff9.a7b47385.1b181ffa.294cb7e7/?pc=https%3A%2F%2Fimg.travel.rakuten.co.jp%2Fimage%2Ftr%2Fapi%2Fhs%2FcHNRi%2F%3Ff_no%3D8778%26f_flg%3DPLAN",
   "reviewUrl": "https://hb.afl.rakuten.co.jp/hgc/1b181ff9.a7b47385.1b181ffa.294cb7e7/?pc=https%3A%2F%2Fimg.travel.rakuten.co.jp%2Fimage%2Ftr%2Fapi%2Fhs%2FRmfmX%2F%3Ff_hotel_no%3D8778",
   "thumbnail": "https://img.travel.rakuten.co.jp/HIMG/90/8778.jpg",
   "imageUrl": "https://img.travel.rakuten.co.jp/share/HOTEL/8778/8778.jpg",
   "special": "アワビや国産牛の夏バイキング！安心の屋内プールや庭遊び、星空露天と源泉１００％の湯で至福の休息を。"
  },
  {
   "hotelNo": 15315,
   "name": "リロステイＶＩＬＬＡ　城崎　ザ・コンドミニアム（旧レイセニット城崎スイートＶＩＬＬＡ）",
   "kana": "りろすていヴぃらきのさきざこんどみにあむ",
   "minCharge": 7480,
   "reviewAverage": 3.79,
   "reviewCount": 1895,
   "access": "ＪＲ山陰本線「城崎温泉」駅から車で約７分(無料送迎車あり※予約制）。北近畿豊岡自動車道「日高神鍋高原」ＩＣより40分。",
   "address1": "兵庫県",
   "address2": "豊岡市小島1220",
   "infoUrl": "https://hb.afl.rakuten.co.jp/hgc/1b181ff9.a7b47385.1b181ffa.294cb7e7/?pc=https%3A%2F%2Fimg.travel.rakuten.co.jp%2Fimage%2Ftr%2Fapi%2Fhs%2FdQ4dX%2F%3Ff_no%3D15315",
   "planUrl": "https://hb.afl.rakuten.co.jp/hgc/1b181ff9.a7b47385.1b181ffa.294cb7e7/?pc=https%3A%2F%2Fimg.travel.rakuten.co.jp%2Fimage%2Ftr%2Fapi%2Fhs%2FcHNRi%2F%3Ff_no%3D15315%26f_flg%3DPLAN",
   "reviewUrl": "https://hb.afl.rakuten.co.jp/hgc/1b181ff9.a7b47385.1b181ffa.294cb7e7/?pc=https%3A%2F%2Fimg.travel.rakuten.co.jp%2Fimage%2Ftr%2Fapi%2Fhs%2FRmfmX%2F%3Ff_hotel_no%3D15315",
   "thumbnail": "https://img.travel.rakuten.co.jp/HIMG/90/15315.jpg",
   "imageUrl": "https://img.travel.rakuten.co.jp/share/HOTEL/15315/15315.jpg",
   "special": "ご夕食・ご朝食はあらかじめお部屋の冷蔵庫にご用意。お好きなタイミングでお召し上がりください。"
  },
  {
   "hotelNo": 50114,
   "name": "ホテルリブマックス豊岡",
   "kana": "ほてるりぶまっくすとよおか",
   "minCharge": 3000,
   "reviewAverage": 3.77,
   "reviewCount": 691,
   "access": "JR豊岡駅より徒歩で10分・車で3分（豊岡市役所方面）",
   "address1": "兵庫県",
   "address2": "豊岡市泉町6-25",
   "infoUrl": "https://hb.afl.rakuten.co.jp/hgc/1b181ff9.a7b47385.1b181ffa.294cb7e7/?pc=https%3A%2F%2Fimg.travel.rakuten.co.jp%2Fimage%2Ftr%2Fapi%2Fhs%2FdQ4dX%2F%3Ff_no%3D50114",
   "planUrl": "https://hb.afl.rakuten.co.jp/hgc/1b181ff9.a7b47385.1b181ffa.294cb7e7/?pc=https%3A%2F%2Fimg.travel.rakuten.co.jp%2Fimage%2Ftr%2Fapi%2Fhs%2FcHNRi%2F%3Ff_no%3D50114%26f_flg%3DPLAN",
   "reviewUrl": "https://hb.afl.rakuten.co.jp/hgc/1b181ff9.a7b47385.1b181ffa.294cb7e7/?pc=https%3A%2F%2Fimg.travel.rakuten.co.jp%2Fimage%2Ftr%2Fapi%2Fhs%2FRmfmX%2F%3Ff_hotel_no%3D50114",
   "thumbnail": "https://img.travel.rakuten.co.jp/HIMG/90/50114.jpg",
   "imageUrl": "https://img.travel.rakuten.co.jp/share/HOTEL/50114/50114.jpg",
   "special": "男女大浴場・サウナ付き！Wi-Fi ・空気清浄機完備！客室タイプ豊富！キャビン貸切可能、団体大歓迎！"
  },
  {
   "hotelNo": 199940,
   "name": "Ｒａｋｕｔｅｎ　ＳＴＡＹ　ＴＥＲＲＡＣＥ　城崎リバーサイド",
   "kana": null,
   "minCharge": 5100,
   "reviewAverage": null,
   "reviewCount": 2,
   "access": "城崎温泉駅から車で7分／コウノトリ但馬空港から車で21分／鳥取コナン空港から車で1時間15分",
   "address1": "兵庫県",
   "address2": "豊岡市城崎町上山1414-4",
   "infoUrl": "https://hb.afl.rakuten.co.jp/hgc/1b181ff9.a7b47385.1b181ffa.294cb7e7/?pc=https%3A%2F%2Fimg.travel.rakuten.co.jp%2Fimage%2Ftr%2Fapi%2Fhs%2FdQ4dX%2F%3Ff_no%3D199940",
   "planUrl": "https://hb.afl.rakuten.co.jp/hgc/1b181ff9.a7b47385.1b181ffa.294cb7e7/?pc=https%3A%2F%2Fimg.travel.rakuten.co.jp%2Fimage%2Ftr%2Fapi%2Fhs%2FcHNRi%2F%3Ff_no%3D199940%26f_flg%3DPLAN",
   "reviewUrl": "https://hb.afl.rakuten.co.jp/hgc/1b181ff9.a7b47385.1b181ffa.294cb7e7/?pc=https%3A%2F%2Fimg.travel.rakuten.co.jp%2Fimage%2Ftr%2Fapi%2Fhs%2FRmfmX%2F%3Ff_hotel_no%3D199940",
   "thumbnail": "https://img.travel.rakuten.co.jp/HIMG/90/199940.jpg",
   "imageUrl": "https://img.travel.rakuten.co.jp/share/HOTEL/199940/199940.jpg",
   "special": "★2026年6月新規OPEN★客室専用の天然温泉を存分に堪能、日常を離れた贅沢なプライベート空間"
  }
 ],
 "listedMatchCount": 17
}